dylunatj/__init__.py
dylunatj/dyluna.py
dylunatj-0.5.dist-info/METADATA
dylunatj-0.5.dist-info/WHEEL
dylunatj-0.5.dist-info/top_level.txt
dylunatj-0.5.dist-info/RECORD
