Metadata-Version: 2.1
Name: dylunatj
Version: 0.5
Summary: A simple wsgi web framework
Home-page: https://github.com/gjergjk71/dylunatj
Author: Gjergj Kadriu
Author-email: tasoha1763@astegol.com
License: Apache2
Classifier: Development Status :: 4 - Beta
Classifier: Intended Audience :: System Administrators
Classifier: License :: OSI Approved :: Apache Software License
Classifier: Programming Language :: Python :: 3
Requires-Python: >=3.7
Requires-Dist: Paste ==2.0.3
Requires-Dist: six ==1.11.0
Requires-Dist: wheel ==0.24.0
Requires-Dist: jinja2 ==3.1.2
